autoIserv/Email.py
autoIserv/Exercise.py
autoIserv/Module.py
autoIserv/Session.py
autoIserv/__init__.py
autoIserv/login.py
autoIserv/util.py
autoIserv/Modules/EmailModule.py
autoIserv/Modules/ExerciseModule.py
autoIserv/Modules/FilesModule.py
autoIserv/Modules/__init__.py
autoIservCredGen/__main__.py
auto_iserv-0.1.12.dist-info/LICENSE
auto_iserv-0.1.12.dist-info/METADATA
auto_iserv-0.1.12.dist-info/WHEEL
auto_iserv-0.1.12.dist-info/entry_points.txt
auto_iserv-0.1.12.dist-info/top_level.txt
auto_iserv-0.1.12.dist-info/RECORD
