Metadata-Version: 2.1
Name: auto-iserv
Version: 0.1.12
Summary: A Library that can be used to create tools to automate Iserv without an API key
Home-page: https://github.com/RedstoneMedia/auto-iserv
Author: RedstoneMedia
License: GNU General Public License v3.0
Keywords: Iserv automation library auto
Platform: UNKNOWN
Requires-Python: >=3.8
License-File: LICENSE
Requires-Dist: PyYAML (>=5.3.1)
Requires-Dist: selenium (==3.141.0)
Requires-Dist: requests (>=2.23.0)
Requires-Dist: urllib3 (>=1.25.8)
Requires-Dist: pycryptodomex (>=3.9.8)
